nsj_rest_lib/__init__.py
nsj_rest_lib/cli.py
nsj_rest_lib/db_pool_config.py
nsj_rest_lib/doc_route_generator.py
nsj_rest_lib/exception.py
nsj_rest_lib/healthcheck_config.py
nsj_rest_lib/injector_factory_base.py
nsj_rest_lib/settings.py
nsj_rest_lib/wsgi.py
nsj_rest_lib/controller/__init__.py
nsj_rest_lib/controller/command_router.py
nsj_rest_lib/controller/constants.py
nsj_rest_lib/controller/controller_util.py
nsj_rest_lib/controller/delete_route.py
nsj_rest_lib/controller/funtion_route_wrapper.py
nsj_rest_lib/controller/get_route.py
nsj_rest_lib/controller/list_route.py
nsj_rest_lib/controller/patch_route.py
nsj_rest_lib/controller/post_route.py
nsj_rest_lib/controller/put_route.py
nsj_rest_lib/controller/route_base.py
nsj_rest_lib/dao/__init__.py
nsj_rest_lib/dao/dao_base.py
nsj_rest_lib/dao/dao_base_conjuntos.py
nsj_rest_lib/dao/dao_base_delete.py
nsj_rest_lib/dao/dao_base_function.py
nsj_rest_lib/dao/dao_base_get.py
nsj_rest_lib/dao/dao_base_insert.py
nsj_rest_lib/dao/dao_base_list.py
nsj_rest_lib/dao/dao_base_partial_of.py
nsj_rest_lib/dao/dao_base_partial_update.py
nsj_rest_lib/dao/dao_base_save_by_function.py
nsj_rest_lib/dao/dao_base_search.py
nsj_rest_lib/dao/dao_base_update.py
nsj_rest_lib/dao/dao_base_util.py
nsj_rest_lib/decorator/__init__.py
nsj_rest_lib/decorator/delete_function_type.py
nsj_rest_lib/decorator/dto.py
nsj_rest_lib/decorator/entity.py
nsj_rest_lib/decorator/function_type.py
nsj_rest_lib/decorator/get_function_type.py
nsj_rest_lib/decorator/insert_function_type.py
nsj_rest_lib/decorator/list_function_type.py
nsj_rest_lib/decorator/opentelemetry.py
nsj_rest_lib/decorator/opentelemetry_base.py
nsj_rest_lib/decorator/update_function_type.py
nsj_rest_lib/descriptor/__init__.py
nsj_rest_lib/descriptor/conjunto_type.py
nsj_rest_lib/descriptor/dto_aggregator.py
nsj_rest_lib/descriptor/dto_field.py
nsj_rest_lib/descriptor/dto_field_validators.py
nsj_rest_lib/descriptor/dto_left_join_field.py
nsj_rest_lib/descriptor/dto_list_field.py
nsj_rest_lib-6.2.0.dist-info/METADATA
nsj_rest_lib-6.2.0.dist-info/WHEEL
nsj_rest_lib-6.2.0.dist-info/top_level.txt
nsj_rest_lib-6.2.0.dist-info/RECORD
