Metadata-Version: 2.4
Name: nsj_rest_lib
Version: 6.2.0
Summary: Biblioteca para construção de APIs Rest Python, de acordo com o guidelines interno, e com paradigma declarativo.
Home-page: https://github.com/Nasajon/nsj_rest_lib
Author: Nasajon Sistemas
Author-email: contact.dev@nasajon.com.br
Project-URL: Source, https://github.com/Nasajon/nsj_rest_lib
Classifier: Development Status :: 3 - Alpha
Classifier: Intended Audience :: Developers
Classifier: Topic :: Software Development :: Libraries
Classifier: Programming Language :: Python :: 3
Requires-Python: >=3.4
Requires-Dist: Flask<3.0.0,>=2.0.3
Requires-Dist: SQLAlchemy<3.0.0,>=1.4.32
Requires-Dist: pg8000<2.0.0,>=1.24.1
Requires-Dist: nsj_gcf_utils<2.0.0,>=1.1.0
Requires-Dist: PyMySQL<2.0.0,>=1.0.2
Requires-Dist: py-healthcheck<2.0.0,>=1.10.1
Requires-Dist: unidecode<2.0.0,>=1.0.22
Requires-Dist: opentelemetry-exporter-otlp<2.0.0,>=1.32.1
Requires-Dist: pyyaml<7.0.0,>=6.0.3
